<SMA>	

	<!--DEFAULT  CONFIGURATION FOR ALL USERS-->
	<layout_name>layout_version_0.1.ejs</layout_name>
	<header_name>header_version_0.1.ejs</header_name>
	<footer_name>footer_version_0.1.ejs</footer_name>
	<logo_name>customLogo.png</logo_name>
	<languages>
		<language_variable>georgian</language_variable>
		<language_variable>english</language_variable>
		<language_variable>russian</language_variable>
		<language_variable>german</language_variable>
	</languages>


	<user_specific>

		<user>
				<user_type>visitor</user_type>
				<layout_name></layout_name>
				<header_name></header_name>
				<footer_name></footer_name>
				<logo_name></logo_name>
				<languages>
					<language_variable>georgian</language_variable>
					<language_variable>english</language_variable>
					<language_variable>russian</language_variable>
					<language_variable>german</language_variable>
				</languages>

				<menus>
					<menu_item>
						<screen_name>home</screen_name>
						<screen_page>
							<page_title>homeTitle</page_title>
							<page_view_name>index.ejs</page_view_name>
						</screen_page>
						<default_list_dataset>
							<data_query>
											<![CDATA[--  Default Data Query

												--  select * from Products
												--select * from product
												
												select p.productGUID				 as UniqueID,
													   p.productName				 as ListItemName,
													   p.productDescriptionShort 	 as Description,
													   p.productQuantityAvailable  as Quantity,
													   p.sellingPrice 			 as Price,
													   mfi.mediaLocationURI		as ImageURI
												from   product p
												left JOIN  productMediaFileInformation mfi
												on mfi.ProductGUID=p.productGUID 
													and mfi.mediaType='ListImage'	
												ORDER BY EFFDATE DESC	

											]]>
							</data_query>
						</default_list_dataset>
						<left_panel>
							<panel_item>
								<screen_name>Not Intake Systems</screen_name>
								<data_query>
									<![CDATA[--  data query  to be executed   on  Home  press 1

										--  select * from Products
										--select * from product
										
										select p.productGUID				 as UniqueID,
											   p.productName				 as ListItemName,
											   p.productDescriptionShort 	 as Description,
											   p.productQuantityAvailable  as Quantity,
											   p.sellingPrice 			 as Price,
											   mfi.mediaLocationURI		as ImageURI
										from   product p
										left JOIN  productMediaFileInformation mfi
										on mfi.ProductGUID=p.productGUID 
											and mfi.mediaType='ListImage'
										where p.ProductCategoryGUID not in (select CategoryGUID from ProductCategory where CategoryName='IntakeSystems')


									]]>
								</data_query>
							</panel_item>
							<panel_item>
								<screen_name>Steering Wheels</screen_name>
								<data_query>
									<![CDATA[--  data query  to be executed   on  Home  press 2

										--  select * from Products
									]]>
								</data_query>
							</panel_item>
							<panel_item>
								<screen_name>Car Electronics</screen_name>
								<data_query>
									<![CDATA[--  data query  to be executed   on  Home  press 3

										--  select * from Products
									]]>
								</data_query>
							</panel_item>
							
						</left_panel>
					</menu_item>
					<menu_item>
						<screen_name>about</screen_name>
						<screen_page>
							<page_title>aboutTitle</page_title>
							<page_view_name>about.ejs</page_view_name>
						</screen_page>
						<default_list_dataset>
							<data_query>
											<![CDATA[--  data query  to be executed   on  about MENU 1


											]]>
										</data_query>
						</default_list_dataset>
						<left_panel>
							<panel_item>
								<screen_name>item 1 for about</screen_name>
								<data_query>
									<![CDATA[--  data query  to be executed   on  about MENU 1

										--  select * from Products
									]]>
								</data_query>
							</panel_item>
							<panel_item>
								<screen_name>item 2 for about</screen_name>
								<data_query>
									<![CDATA[--  data query  to be executed   on  about MENU 2

										--  select * from Products
									]]>
								</data_query>
							</panel_item>
							<panel_item>
								<screen_name>item 3 for about</screen_name>
								<data_query>
									<![CDATA[--  data query  to be executed   about MENU 3

										--  select * from Products
									]]>
								</data_query>
							</panel_item>
						</left_panel>
					</menu_item>
					<menu_item>
						<screen_name>contact</screen_name>
						<screen_page>
							<page_title>SMA Contact Page</page_title>
							<page_view_name>contact.ejs</page_view_name>
						</screen_page>
						<default_list_dataset>
							<data_query>
											<![CDATA[--  data query  to be executed   on  Home  press 1

											

											]]>
										</data_query>
						</default_list_dataset>
					</menu_item>
					<menu_item>
						<screen_name>tESTER</screen_name>
						<screen_page>
							<page_title>SMA tESTER Page</page_title>
							<page_view_name>tESTER.ejs</page_view_name>
						</screen_page>
						<default_list_dataset>
							<data_query>
											<![CDATA[--  data query  to be executed   on  Home  press 1

											

											]]>
										</data_query>
						</default_list_dataset>
					</menu_item>
				</menus>
				
				<default_page>
					<page_title>SMA Application by OzKart</page_title>
					<page_view_name>index.ejs</page_view_name>
				</default_page>

				<additional_menu>
					<menu_item>
						<screen_name>login</screen_name>
						<screen_page>
							<page_title>login</page_title>
							<page_view_name>login.ejs</page_view_name>
						</screen_page>
					</menu_item>

					<menu_item>
						<screen_name>register</screen_name>
						<screen_page>
							<page_title>register</page_title>
							<page_view_name>register.ejs</page_view_name>
						</screen_page>
					</menu_item>
				</additional_menu>

		</user>
		<user>
			<user_type>client</user_type>
			<layout_name></layout_name>
		    <header_name></header_name>
		    <footer_name></footer_name>
		    <logo_name></logo_name>


		    <menus>
				<menu_item>
					<screen_name></screen_name>
					<screen_page>
						<page_title></page_title>
						<page_view_name></page_view_name>
					</screen_page>
					<default_list_dataset>
						<data_query>
										<![CDATA[--  data query  to be executed   on  Home  press 1


										]]>
						</data_query>
					</default_list_dataset>
				</menu_item>				
		    </menus>
		    <additional_menu>
					<menu_item>
						<screen_name>log out</screen_name>
						<screen_page>
							<page_title>log out</page_title>
							<page_view_name>logout.ejs</page_view_name>
						</screen_page>
					</menu_item>

					
			</additional_menu>

			<sidebar>
				<sidebar_item>
					<screen_name></screen_name>
					<screen_page>
						<page_title></page_title>
						<page_view_name></page_view_name>
					</screen_page>
				</sidebar_item>
			</sidebar>
			<default_page>
					<page_title>SMA Application by OzKart client profile</page_title>
					<page_view_name>index.ejs</page_view_name>
			</default_page>
			
		</user>
		
		
	</user_specific>
</SMA>